witshape/__init__.py
witshape/__main__.py
witshape/logconf_witshape.yml
witshape/version.py
witshape/app/app.py
witshape/app/pgvector.py
witshape/app/features/cli/pgvector_base.py
witshape/app/features/cli/witshape_pgvector_createdb.py
witshape/app/features/cli/witshape_pgvector_down.py
witshape/app/features/cli/witshape_pgvector_embed.py
witshape/app/features/cli/witshape_pgvector_install.py
witshape/app/features/cli/witshape_pgvector_search.py
witshape/app/features/cli/witshape_pgvector_uninstall.py
witshape/app/features/cli/witshape_pgvector_up.py
witshape/app/features/web/witshape_web_gui.py
witshape/app/features/web/witshape_web_pgvector_search.py
witshape/app/features/web/witshape_web_versions_witshape.py
witshape/docker/pgvectordb/Dockerfile
witshape/docker/pgvectordb/docker-compose.yml
witshape/extensions/features.yml
witshape/extensions/user_list.yml
witshape/web/assets/witshape/favicon.ico
witshape/web/assets/witshape/icon.png
witshape-0.1.4.2.dist-info/LICENSE
witshape-0.1.4.2.dist-info/METADATA
witshape-0.1.4.2.dist-info/WHEEL
witshape-0.1.4.2.dist-info/entry_points.txt
witshape-0.1.4.2.dist-info/top_level.txt
witshape-0.1.4.2.dist-info/RECORD
