Metadata-Version: 2.1
Name: witshape
Version: 0.1.4.2
Summary: witshape: This is an implementation for using an arbitrary file system as an external knowledge of Dify.
Home-page: https://github.com/hamacom2004jp/witshape
Download-URL: https://github.com/hamacom2004jp/witshape
Author: hamacom2004jp
Author-email: hamacom2004jp@gmail.com
Maintainer: hamacom2004jp
Maintainer-email: hamacom2004jp@gmail.com
License: MIT
Keywords: cli restapi redis fastapi
Classifier: Development Status :: 4 - Beta
Classifier: Intended Audience :: Developers
Classifier: Intended Audience :: Information Technology
Classifier: Intended Audience :: System Administrators
Classifier: License :: OSI Approved :: MIT License
Classifier: Natural Language :: Japanese
Classifier: Programming Language :: Python
Classifier: Topic :: Utilities
Requires-Python: >=3.10
License-File: LICENSE
Requires-Dist: cmdbox>=0.2.5.3
Requires-Dist: chardet
Requires-Dist: langchain-community
Requires-Dist: langchain-google-vertexai
Requires-Dist: langchain-ollama
Requires-Dist: langchain-openai
Requires-Dist: langchain-postgres
Requires-Dist: markdown
Requires-Dist: psycopg[binary]
Requires-Dist: pdfplumber
Requires-Dist: requests
Requires-Dist: unstructured
